db_controller/__init__.py
db_controller/config.py
db_controller/controller.py
algo_db_controller-0.1.dist-info/METADATA
algo_db_controller-0.1.dist-info/WHEEL
algo_db_controller-0.1.dist-info/top_level.txt
algo_db_controller-0.1.dist-info/RECORD
