Metadata-Version: 2.1
Name: algo-db-controller
Version: 0.1
Summary: Controls everything db related for algo
Home-page: UNKNOWN
Author: Afzal SH @ Tarams
Author-email: afzal.hameed@tarams.com
License: MIT
Platform: UNKNOWN
Requires-Dist: psycopg2
